__init__.py
proxop/___main__.py
proxop/__init__.py
proxop/indicator/BoxConstraint.py
proxop/indicator/EpiAbsValue.py
proxop/indicator/EpiDistance.py
proxop/indicator/EpiExp.py
proxop/indicator/EpiHingeLoss.py
proxop/indicator/EpiL2Norm.py
proxop/indicator/EpiLinfNorm.py
proxop/indicator/EpiLog.py
proxop/indicator/EpiMax.py
proxop/indicator/EpiPower.py
proxop/indicator/EpiSquaredHingeLoss.py
proxop/indicator/EpiSupport.py
proxop/indicator/ExtendedSimplex.py
proxop/indicator/Hyperplane.py
proxop/indicator/Hyperslab.py
proxop/indicator/L1Ball.py
proxop/indicator/L1_2Ball.py
proxop/indicator/L2Ball.py
proxop/indicator/LinfBall.py
proxop/indicator/LogProjection.py
proxop/indicator/MonotoneCone.py
proxop/indicator/PositiveL2Ball.py
proxop/indicator/Simplex.py
proxop/indicator/__init__.py
proxop/multi/AbsDiff.py
proxop/multi/AffineBarrier.py
proxop/multi/ChiSquare.py
proxop/multi/Hellinger.py
proxop/multi/HyperslabBarrier.py
proxop/multi/Ialpha.py
proxop/multi/InvPenaltyLogDet.py
proxop/multi/Jeffrey.py
proxop/multi/Kullback.py
proxop/multi/L1Norm.py
proxop/multi/L21columns.py
proxop/multi/L21rows.py
proxop/multi/L2BallBarrier.py
proxop/multi/L2DownConv.py
proxop/multi/L2Norm.py
proxop/multi/L2Positive.py
proxop/multi/Linf.py
proxop/multi/Linf1.py
proxop/multi/LogDet.py
proxop/multi/Max.py
proxop/multi/NeumannEntropy.py
proxop/multi/NuclearBall.py
proxop/multi/NuclearBlocks.py
proxop/multi/NuclearLogDet.py
proxop/multi/NuclearNorm.py
proxop/multi/NuclearNormRidge.py
proxop/multi/PermutationInvariant.py
proxop/multi/PersAbsDiff.py
proxop/multi/PersHuber.py
proxop/multi/PersSqrt.py
proxop/multi/PersSquare.py
proxop/multi/PersVapnik.py
proxop/multi/Rank.py
proxop/multi/RankRidge.py
proxop/multi/Renyi.py
proxop/multi/Schatten3Penalty.py
proxop/multi/Schatten3_2Penalty.py
proxop/multi/Schatten4Penalty.py
proxop/multi/Schatten4_3Penalty.py
proxop/multi/SchattenPenaltyLogDet.py
proxop/multi/SoftmaxActi.py
proxop/multi/Spectral.py
proxop/multi/SquaredFrobeniusNormLogDet.py
proxop-1.0.6.dist-info/LICENSE
proxop-1.0.6.dist-info/METADATA
proxop-1.0.6.dist-info/WHEEL
proxop-1.0.6.dist-info/entry_points.txt
proxop-1.0.6.dist-info/top_level.txt
proxop-1.0.6.dist-info/RECORD
