Metadata-Version: 2.1
Name: proxop
Version: 1.0.6
Summary: This Python library provides an implementation of the proximity operator of several functions to solve non-smooth optimization problems.
Author-email: mbayediongue <mbayediongue22@gmail.com>
Maintainer-email: mbayediongue <mbayediongue22@gmail.com>
License: CeCILL-B FREE SOFTWARE LICENSE AGREEMENT
Project-URL: Homepage, http://proximity-operator.net/
Keywords: proximal algorithms,proximity operator,large-scale optimization,convex optimization,inverse problems
Classifier: License :: CeCILL-B Free Software License Agreement (CECILL-B)
Classifier: Programming Language :: Python
Classifier: Programming Language :: Python :: 3
Requires-Python: >=3.8
License-File: LICENSE
Requires-Dist: numpy (>=1.14.0)
Requires-Dist: scipy (>=1.8.0)
